Workbook

Sheet Assumption
H1: Financial Statement
B2: This Assumption Tab is meant to be as detailed as possible for easier intepretation | H2: Category
H3: Subcategory
A5: x | B5: Income Statement
B6: Line-Item | E6: Assumption
B7: Revenue | E7: Average of past 2 years growth rate and held constant
B8: COGS | E8: Derived from Revenue * (1-Gross Profit Margin)
B9: Gross Profit Margin | E9: Average of past 3 years and held constant
B10: Other Income & Operating Expenses | E10: Average of past 3 years in terms of % of revenue
B11: Fair value loss/gain on biological assets | E11: Inconsistent and assumed zero
B12: Interest Income | E12: Calculated as a percentage of opening cash balance to find out interest rate ->Highly volatile so kept current year interest rate (smaller % = more prudence)
B13: Interest Expense | E13: Calculated as a percentage of opening total debt to infer interest rate -> Used the average of both interest rates and kept constant
B14: Tax Expense | E14: Calculated historical % by taking tax expense / pre-tax profit -> Used the average and kept constant
A17: x | B17: Balance Sheet
B18: Non-Current Assets | E18: Assumption
B19: PPE Depreciation | E19: Found implied depreciation rate (Depreciation of PPE / Opening PPE) -> Used average rate and kept constant
B20: PPE Additions | E20: Calculated additions of PPE as a multiple of depreciation -> A falling trend -> -0.2x YoY
B21: PPE | E21: PPE Closing Balance = PPE Opening Balance - Depreciation + Additions
B22: Intangibles | E22: Amount too small to have any meaningful rate changes -> Held constant based on FY2025 values
B23: ROU Assets (Depreciation and Additions) | E23: Same approach as PPE, but implied depreciation rate and addition multiple too volatile, used FY2025 value and held constant
B24: ROU Assets | E24: ROU Closing = ROU Opening - Depreciation + Additions
B25: Biological Assets (Depreciation and Disposal) | E25: Same approach as PPE but no obvious trend, average of past values used and held constant
B26: Biological Assets | E26: Biological Assets (BA) Closing = BA Opening - Disposals + Additions
B27: Other Non-Current Assets | E27: Projected to grow in line with revenue growth
B29: Current Assets | E29: Assumption
B30: Inventories | E30: Scale with COGS Growth
... B52: Retained Earnings | E52: Retained Earnings (Opening) + Net Income - Dividend Payout (Kept constant at 2025 level) = Closing Retained Earnings
A55: x | B55: Statement of Cash Flows
B56: Most assumptions made in previous statements

Sheet Grouping OR Separating
B2: GROUPING | D2: FY2023A | E2: FY2024A | F2: FY2025A | J2: SEPARATING | L2: FY2023A | M2: FY2024A | N2: FY2025A
B3: Income Statement | J3: Income Statement
B5: Other income | D5: =9162-110 -> 9052 | E5: 11952 | F5: 6829
B6: Fair value (loss)/gain on biological assets | D6: 110 | E6: 502 | F6: -2556
B8: Selling and distribution expenses | D8: -51711 | E8: -69727 | F8: -88063
B9: Administrative expenses | D9: -35872 | E9: -67425 | F9: -88755
B10: Other expenses | D10: -7592 | E10: -6337 | F10: -10846
B11: Operating Expenses | D11: =SUM(D8:D10) -> -95175 | E11: =SUM(E8:E10) -> -143489 | F11: =SUM(F8:F10) -> -187664
B13: Balance Sheet | J13: Balance Sheet
B15: Trade and other receivables | D15: 1130 | E15: 563 | F15: 268 | J15: Short-Term Borrowing | L15: 92934 | M15: 67648 | N15: 91622
B16: Deferred tax assets | D16: 7673 | E16: 8926 | F16: 9371 | J16: Revolving Line of Credit | L16: 14760 | M16: 0 | N16: 0
B17: Other NCAs | D17: =SUM(D15:D16) -> 8803 | E17: =SUM(E15:E16) -> 9489 | F17: =SUM(F15:F16) -> 9639 | J17: Short-Term Borrowing (w/o revolver) | L17: =L15-L16 -> 78174 | M17: =M15-M16 -> 67648 | N17: =N15-N16 -> 91622
B19: Current Tax Assets | D19: 1541 | E19: 4509 | F19: 5446
B20: Derivative Financial Assets | D20: 685 | E20: 893 | F20: 86
B21: Other Investments | D21: 155790 | E21: 99944 | F21: 64037
B22: Other CAs | D22: =SUM(D19:D21) -> 158016 | E22: =SUM(E19:E21) -> 105346 | F22: =SUM(F19:F21) -> 69569
B24: Deferred Tax Liabilities | D24: 7731 | E24: 19161 | F24: 24345
B25: Deferred Income | D25: 6226 | E25: 5955 | F25: 6703
B26: Put Option Liability | D26: - | E26: 36955 | F26: 55833
B27: Other NCLs | D27: =SUM(D24:D26) -> 13957 | E27: =SUM(E24:E26) -> 62071 | F27: =SUM(F24:F26) -> 86881
B29: Deferred Income | D29: 271 | E29: 271 | F29: 943
B30: Derivative Financial Liabilities | D30: 1695 | E30: - | F30: 428
B31: Current Tax Liabilities | D31: - | E31: 648 | F31: 1116
B32: Other CLs | D32: =SUM(D29:D31) -> 1966 | E32: =SUM(E29:E31) -> 919 | F32: =SUM(F29:F31) -> 2487

Sheet 3-Statement
A1: RM'000
D2: FY2023A | E2: FY2024A | F2: FY2025A | G2: FY2026E | H2: FY2027E | I2: FY2028E | J2: FY2029E | K2: FY2030E
A3: x | B3: Income Statement
B4: Revenue | D4: 629691 | E4: 810411 | F4: 981181 | G4: =F4*(1+G21) -> 1225356.8 | H4: =G4*(1+H21) -> 1530298 | I4: =H4*(1+I21) -> 1911126.5 | J4: =I4*(1+J21) -> 2386727.7 | K4: =J4*(1+K21) -> 2980686.5
B5: (-) COGS | D5: -480038 | E5: -594368 | F5: -665947 | G5: =-G4*(1-G23) -> -888168.97 | H5: =-H4*(1-H23) -> -1109197.9 | I5: =-I4*(1-I23) -> -1385231.8 | J5: =-J4*(1-J23) -> -1729959.3 | K5: =-K4*(1-K23) -> -2160475.4
B6: Gross Profit | D6: =SUM(D4:D5) -> 149653 | E6: =SUM(E4:E5) -> 216043 | F6: =SUM(F4:F5) -> 315234 | G6: =SUM(G4:G5) -> 337187.83 | H6: =SUM(H4:H5) -> 421100.08 | I6: =SUM(I4:I5) -> 525894.66 | J6: =SUM(J4:J5) -> 656768.31 | K6: =SUM(K4:K5) -> 820211.07
B7: Other Income | D7: ='Grouping OR Separating'!D5 -> 9052 | E7: ='Grouping OR Separating'!E5 -> 11952 | F7: ='Grouping OR Separating'!F5 -> 6829 | G7: =G4*G24 -> 14738.329 | H7: =H4*H24 -> 18406.096 | I7: =I4*I24 -> 22986.62 | J7: =J4*J24 -> 28707.049 | K7: =K4*K24 -> 35851.058
B8: Operating Expenses | D8: ='Grouping OR Separating'!D11 -> -95175 | E8: ='Grouping OR Separating'!E11 -> -143489 | F8: ='Grouping OR Separating'!F11 -> -187664 | G8: =-G4*G25 -> -212177.07 | H8: =-H4*H25 -> -264979.26 | I8: =-I4*I25 -> -330921.76 | J8: =-J4*J25 -> -413274.64 | K8: =-K4*K25 -> -516121.78
B9: Fair value (loss)/gain on biological assets | D9: ='Grouping OR Separating'!D6 -> 110 | E9: ='Grouping OR Separating'!E6 -> 502 | F9: ='Grouping OR Separating'!F6 -> -2556 | G9: 0 | H9: 0 | I9: 0 | J9: 0 | K9: 0
B10: Operating Profit (EBIT) | D10: =SUM(D6:D9) -> 63640 | E10: =SUM(E6:E9) -> 85008 | F10: =SUM(F6:F9) -> 131843 | G10: =SUM(G6:G9) -> 139749.09 | H10: =SUM(H6:H9) -> 174526.91 | I10: =SUM(I6:I9) -> 217959.52 | J10: =SUM(J6:J9) -> 272200.72 | K10: =SUM(K6:K9) -> 339940.34
B12: Interest Income | D12: 473 | E12: 937 | F12: 1062 | G12: =G26*F61 -> 1073.2833 | H12: =H26*G61 -> 1118.6144 | I12: =I26*H61 -> 1396.9918 | J12: =J26*I61 -> 1744.6459 | K12: =K26*J61 -> 2178.8168
B13: Interest Expense | D13: -11939 | E13: -16880 | F13: -17672 | G13: =G27*-F91 -> -19149.26 | H13: =H27*-G91 -> -22261.021 | I13: =I27*-H91 -> -26591.073 | J13: =J27*-I91 -> -30517.195 | K13: =K27*-J91 -> -33845.68
B14: Pre-Tax Profit (EBT) | D14: =D10+D12+D13 -> 52174 | E14: =E10+E12+E13 -> 69065 | F14: =F10+F12+F13 -> 115233 | G14: =G10+G12+G13 -> 121673.11 | H14: =H10+H12+H13 -> 153384.51 | I14: =I10+I12+I13 -> 192765.44 | J14: =J10+J12+J13 -> 243428.17 | K14: =K10+K12+K13 -> 308273.48
B16: Tax Expense | D16: -2240 | E16: -5784 | F16: -7918 | G16: =-G14*G28 -> -7924.7079 | H16: =-H14*H28 -> -9990.1074 | I16: =-I14*I28 -> -12555.032 | J16: =-J14*J28 -> -15854.754 | K16: =-K14*K28 -> -20078.202
B17: Net Income (Earnings) | D17: =D14+D16 -> 49934 | E17: =E14+E16 -> 63281 | F17: =F14+F16 -> 107315 | G17: =G14+G16 -> 113748.4 | H17: =H14+H16 -> 143394.4 | I17: =I14+I16 -> 180210.41 | J17: =J14+J16 -> 227573.42 | K17: =K14+K16 -> 288195.28
A20: x | B20: Assumptions
B21: Revenue Growth | E21: =E4/D4-1 -> 0.28699791 | F21: =F4/E4-1 -> 0.21072024 | G21: =AVERAGE(E21:F21) -> 0.24885907 | H21: =G21 -> 0.24885907 | I21: =H21 -> 0.24885907 | J21: =I21 -> 0.24885907 | K21: =J21 -> 0.24885907
B22: COGS Growth | E22: =E5/D5-1 -> 0.23816864 | F22: =F5/E5-1 -> 0.12042876 | G22: =G5/F5-1 -> 0.33369317 | H22: =H5/G5-1 -> 0.24885907 | I22: =I5/H5-1 -> 0.24885907 | J22: =J5/I5-1 -> 0.24885907 | K22: =K5/J5-1 -> 0.24885907
B23: Gross Profit Margin | D23: =D6/D4 -> 0.23766101 | E23: =E6/E4 -> 0.26658449 | F23: =F6/F4 -> 0.32128017 | G23: =AVERAGE(D23:F23) -> 0.27517522 | H23: =G23 -> 0.27517522 | I23: =H23 -> 0.27517522 | J23: =I23 -> 0.27517522 | K23: =J23 -> 0.27517522
B24: Other Income - % of Revenue | D24: =D7/D4 -> 0.014375305 | E24: =E7/E4 -> 0.014748072 | F24: =F7/F4 -> 0.0069599799 | G24: =AVERAGE(D24:F24) -> 0.012027786 | H24: =G24 -> 0.012027786 | I24: =H24 -> 0.012027786 | J24: =I24 -> 0.012027786 | K24: =J24 -> 0.012027786
B25: Operating Expenses - % of Revenue | D25: =-D8/D4 -> 0.15114556 | E25: =-E8/E4 -> 0.17705707 | F25: =-F8/F4 -> 0.19126339 | G25: =AVERAGE(D25:F25) -> 0.17315534 | H25: =G25 -> 0.17315534 | I25: =H25 -> 0.17315534 | J25: =I25 -> 0.17315534 | K25: =J25 -> 0.17315534
B26: Interest Income - % of Cash | E26: =E12/D61 -> 0.040792338 | F26: =F12/E61 -> 0.018257775 | G26: =F26 -> 0.018257775 | H26: =G26 -> 0.018257775 | I26: =H26 -> 0.018257775 | J26: =I26 -> 0.018257775 | K26: =J26 -> 0.018257775
B27: Interest Expense - % of Total Debt | E27: =-E13/D91 -> 0.04869198 | F27: =-F13/E91 -> 0.041024689 | G27: =AVERAGE(D27:F27) -> 0.044858334 | H27: =G27 -> 0.044858334 | I27: =H27 -> 0.044858334 | J27: =I27 -> 0.044858334 | K27: =J27 -> 0.044858334
B28: Tax Rate | D28: =-D16/D14 -> 0.042933262 | E28: =-E16/E14 -> 0.083747195 | F28: =-F16/F14 -> 0.068712955 | G28: =AVERAGE(D28:F28) -> 0.065131137 | H28: =G28 -> 0.065131137 | I28: =H28 -> 0.065131137 | J28: =I28 -> 0.065131137 | K28: =J28 -> 0.065131137
B30: Depreciation of PPE | D30: -31064 | E30: -40165 | F30: -48080 | G30: =-F52*G32 -> -49873.454 | H30: =-G52*H32 -> -55043.308 | I30: =-H52*I32 -> -59679.835 | J30: =-I52*J32 -> -63547.618 | K30: =-J52*K32 -> -66431.636
B31: Additions of PPE | D31: 117834 | E31: 105976 | F31: 109010 | G31: =-G30*G33 -> 103101.54 | H31: =-H30*H33 -> 102780.33 | I31: =-I30*I33 -> 99501.974 | J31: =-J30*J33 -> 93241.061 | K31: =-K30*K33 -> 84186.347
B32: Implied Depreciation Rate (PPE) | E32: =-E30/D52 -> 0.097049492 | F32: =-F30/E52 -> 0.097203381 | G32: =AVERAGE(E32:F32) -> 0.097126437 | H32: =G32 -> 0.097126437 | I32: =H32 -> 0.097126437 | J32: =I32 -> 0.097126437 | K32: =J32 -> 0.097126437
B33: Additions as multiple of Depreciation | D33: =D31/-D30 -> 3.7932655 | E33: =E31/-E30 -> 2.6385161 | F33: =F31/-F30 -> 2.2672629 | G33: =F33-0.2 -> 2.0672629 | H33: =G33-0.2 -> 1.8672629 | I33: =H33-0.2 -> 1.6672629 | J33: =I33-0.2 -> 1.4672629 | K33: =J33-0.2 -> 1.2672629
B35: Amortization of Intangible Assets | D35: -235 | E35: -263 | F35: -274 | G35: =F35 -> -274 | H35: =G35 -> -274 | I35: =H35 -> -274 | J35: =I35 -> -274 | K35: =J35 -> -274
B36: Purchases of Intangibles | D36: 324.495 | E36: 1124 | F36: 623 | G36: =F36 -> 623 | H36: =G36 -> 623 | I36: =H36 -> 623 | J36: =I36 -> 623 | K36: =J36 -> 623
B38: Depreciation of ROU Assets | D38: -1928 | E38: -8158 | F38: -10163 | G38: =-F54*G40 -> -11188.689 | H38: =-G54*H40 -> -12834.024 | I38: =-H54*I40 -> -14721.313 | J38: =-I54*J40 -> -16886.133 | K38: =-J54*K40 -> -19369.298
B39: Additions of ROU Assets | D39: 6888 | E39: 11952 | F39: 15034 | G39: =-G38*G41 -> 16551.288 | H39: =-H38*H41 -> 18985.213 | I39: =-I38*I41 -> 21777.055 | J39: =-J38*J41 -> 24979.447 | K39: =-K38*K41 -> 28652.762
B40: Implied Depreciation Rate (ROU) | E40: =-E38/D54 -> 0.42097115 | F40: =-F38/E54 -> 0.30681681 | G40: =F40 -> 0.30681681 | H40: =G40 -> 0.30681681 | I40: =H40 -> 0.30681681 | J40: =I40 -> 0.30681681 | K40: =J40 -> 0.30681681
B41: Additions as multiple of Depreciation | D41: =D39/-D38 -> 3.5726141 | E41: =E39/-E38 -> 1.465065 | F41: =F39/-F38 -> 1.4792876 | G41: =F41 -> 1.4792876 | H41: =G41 -> 1.4792876 | I41: =H41 -> 1.4792876 | J41: =I41 -> 1.4792876 | K41: =J41 -> 1.4792876
B43: Biological Asset Disposal | D43: =-(8209+294) -> -8503 | E43: -5776 | F43: -6025 | G43: =-F55*G45 -> -6767.2582 | H43: =-G55*H45 -> -7753.1927 | I43: =-H55*I45 -> -8882.7699 | J43: =-I55*J45 -> -10176.917 | K43: =-J55*K45 -> -11659.611
B44: Additions of Biological Asset | D44: 29364 | E44: 23538 | F44: 24323 | G44: =-G43*G46 -> 27448.51 | H44: =-H43*H46 -> 31447.535 | I44: =-I43*I46 -> 36029.185 | J44: =-J43*J46 -> 41278.344 | K44: =-K43*K46 -> 47292.263
B45: Implied Disposal Rate (Biological Assets) | E45: =-E43/D55 -> 0.0501415 | F45: =-'3-Statement'!F43/'3-Statement'!E55 -> 0.045204226 | G45: =AVERAGE(E45:F45) -> 0.047672863 | H45: =G45 -> 0.047672863 | I45: =H45 -> 0.047672863 | J45: =I45 -> 0.047672863 | K45: =J45 -> 0.047672863
B46: Additions as multiple of Disposal | D46: =D44/-D43 -> 3.4533694 | E46: =E44/-E43 -> 4.0751385 | F46: =F44/-F43 -> 4.0370124 | G46: =AVERAGE(E46:F46) -> 4.0560755 | H46: =G46 -> 4.0560755 | I46: =H46 -> 4.0560755 | J46: =I46 -> 4.0560755 | K46: =J46 -> 4.0560755
B48: Memo: Total CAPEX | D48: =D31+D36+D39+D44 -> 154410.49 | E48: =E31+E36+E39+E44 -> 142590 | F48: =F31+F36+F39+F44 -> 148990 | G48: =G31+G36+G39+G44 -> 147724.34 | H48: =H31+H36+H39+H44 -> 153836.08 | I48: =I31+I36+I39+I44 -> 157931.21 | J48: =J31+J36+J39+J44 -> 160121.85 | K48: =K31+K36+K39+K44 -> 160754.37
A51: x | B51: Balance Sheet
B52: PP&E | D52: 413861 | E52: 494633 | F52: 513490 | G52: =F52+G30+G31 -> 566718.09 | H52: =G52+H30+H31 -> 614455.11 | I52: =H52+I30+I31 -> 654277.25 | J52: =I52+J30+J31 -> 683970.69 | K52: =J52+K30+K31 -> 701725.4
B53: Intangible Assets | D53: 19317 | E53: 112826 | F53: 111126 | G53: =F53+G35+G36 -> 111475 | H53: =G53+H35+H36 -> 111824 | I53: =H53+I35+I36 -> 112173 | J53: =I53+J35+J36 -> 112522 | K53: =J53+K35+K36 -> 112871
B54: ROU Assets | D54: 19379 | E54: 33124 | F54: 36467 | G54: =F54+G38+G39 -> 41829.6 | H54: =G54+H38+H39 -> 47980.789 | I54: =H54+I38+I39 -> 55036.531 | J54: =I54+J38+J39 -> 63129.846 | K54: =J54+K38+K39 -> 72413.31
B55: Biological Assets | D55: 115194 | E55: 133284 | F55: 141952 | G55: =F55+G43+G44 -> 162633.25 | H55: =G55+H43+H44 -> 186327.59 | I55: =H55+I43+I44 -> 213474.01 | J55: =I55+J43+J44 -> 244575.44 | K55: =J55+K43+K44 -> 280208.09
B56: Other Non-Current Assets | D56: ='Grouping OR Separating'!D17 -> 8803 | E56: ='Grouping OR Separating'!E17 -> 9489 | F56: ='Grouping OR Separating'!F17 -> 9639 | G56: =F56*(1+G21) -> 12037.753 | H56: =G56*(1+H21) -> 15033.457 | I56: =H56*(1+I21) -> 18774.669 | J56: =I56*(1+J21) -> 23446.915 | K56: =J56*(1+K21) -> 29281.893
B57: Total Non-Current Assets | D57: =SUM(D52:D56) -> 576554 | E57: =SUM(E52:E56) -> 783356 | F57: =SUM(F52:F56) -> 812674 | G57: =SUM(G52:G56) -> 894693.69 | H57: =SUM(H52:H56) -> 975620.95 | I57: =SUM(I52:I56) -> 1053735.5 | J57: =SUM(J52:J56) -> 1127644.9 | K57: =SUM(K52:K56) -> 1196499.7
B59: Inventories | D59: 173675 | E59: 156299 | F59: 175332 | G59: =F59*(1+G22) -> 233839.09 | H59: =G59*(1+H22) -> 292032.07 | I59: =H59*(1+I22) -> 364706.9 | J59: =I59*(1+J22) -> 455467.52 | K59: =J59*(1+K22) -> 568814.75
B60: Receivables | D60: 131421 | E60: 176433 | F60: 206665 | G60: =F60*(1+G21) -> 258095.46 | H60: =G60*(1+H21) -> 322324.86 | I60: =H60*(1+I21) -> 402538.32 | J60: =I60*(1+J21) -> 502713.64 | K60: =J60*(1+K21) -> 627818.49
B61: Cash and cash equivalents | D61: 22970 | E61: 58167 | F61: 58785 | G61: =F61+G155 -> 61267.84 | H61: =G61+H155 -> 76514.898 | I61: =H61+I155 -> 95556.324 | J61: =I61+J155 -> 119336.38 | K61: =J61+K155 -> 149034.32
B62: Other Current Assets | D62: ='Grouping OR Separating'!D22 -> 158016 | E62: ='Grouping OR Separating'!E22 -> 105346 | F62: ='Grouping OR Separating'!F22 -> 69569 | G62: =F62*(1+G21) -> 86881.877 | H62: =G62*(1+H21) -> 108503.22 | I62: =H62*(1+I21) -> 135505.23 | J62: =I62*(1+J21) -> 169226.94 | K62: =J62*(1+K21) -> 211340.6
B63: Assets classified as held for sale | D63: 0 | E63: 0 | F63: 28144 | G63: 0 | H63: 0 | I63: 0 | J63: 0 | K63: 0
B64: Total Current Assets | D64: =SUM(D59:D63) -> 486082 | E64: =SUM(E59:E63) -> 496245 | F64: =SUM(F59:F63) -> 538495 | G64: =SUM(G59:G63) -> 640084.27 | H64: =SUM(H59:H63) -> 799375.05 | I64: =SUM(I59:I63) -> 998306.78 | J64: =SUM(J59:J63) -> 1246744.5 | K64: =SUM(K59:K63) -> 1557008.2
B66: Total Assets | D66: =D57+D64 -> 1062636 | E66: =E57+E64 -> 1279601 | F66: =F57+F64 -> 1351169 | G66: =G57+G64 -> 1534778 | H66: =H57+H64 -> 1774996 | I66: =I57+I64 -> 2052042.2 | J66: =J57+J64 -> 2374389.4 | K66: =K57+K64 -> 2753507.9
B68: Long-Term Borrowing | D68: 243318 | E68: 338365 | F68: 306282 | G68: =F68 -> 306282 | H68: =G68 -> 306282 | I68: =H68 -> 306282 | J68: =I68 -> 306282 | K68: =J68 -> 306282
B69: Lease Liabilities (Long-Term) | D69: 8124 | E69: 16742 | F69: 20590 | G69: =G98 -> 21648.532 | H69: =H98 -> 23738.914 | I69: =I98 -> 26723.529 | J69: =J98 -> 30418.836 | K69: =K98 -> 34783.431
B70: Other Non-Current Liabilities | D70: ='Grouping OR Separating'!D27 -> 13957 | E70: ='Grouping OR Separating'!E27 -> 62071 | F70: ='Grouping OR Separating'!F27 -> 86881 | G70: =F70 -> 86881 | H70: =G70 -> 86881 | I70: =H70 -> 86881 | J70: =I70 -> 86881 | K70: =J70 -> 86881
B71: Total Non-Current Liabilities | D71: =SUM(D68:D70) -> 265399 | E71: =SUM(E68:E70) -> 417178 | F71: =SUM(F68:F70) -> 413753 | G71: =SUM(G68:G70) -> 414811.53 | H71: =SUM(H68:H70) -> 416901.91 | I71: =SUM(I68:I70) -> 419886.53 | J71: =SUM(J68:J70) -> 423581.84 | K71: =SUM(K68:K70) -> 427946.43
B73: Short-Term Borrowing | D73: ='Grouping OR Separating'!L17 -> 78174 | E73: ='Grouping OR Separating'!M17 -> 67648 | F73: ='Grouping OR Separating'!N17 -> 91622 | G73: =F73*(1+G21) -> 114422.97 | H73: =G73*(1+H21) -> 142898.16 | I73: =H73*(1+I21) -> 178459.66 | J73: =I73*(1+J21) -> 222870.97 | K73: =J73*(1+K21) -> 278334.43
B74: Revolving Line of Credit | D74: ='Grouping OR Separating'!L16 -> 14760 | E74: 0 | F74: 0 | G74: =F74+G159 -> 45573.551 | H74: =G74+H159 -> 110731.41 | I74: =H74+I159 -> 158560.32 | J74: =I74+J159 -> 183232.67 | K74: =J74+K159 -> 178012.72
B75: Payables | D75: 64142 | E75: 92875 | F75: 106679 | G75: =F75*(1+G22) -> 142277.05 | H75: =G75*(1+H22) -> 177683.99 | I75: =H75*(1+I22) -> 221902.26 | J75: =I75*(1+J22) -> 277124.65 | K75: =J75*(1+K22) -> 346089.64
B76: Lease Liabilities (Short-Term) | D76: 2293 | E76: 8010 | F76: 8389 | G76: =G96 -> 8324.5621 | H76: =H96 -> 9128.382 | I76: =I96 -> 10276.063 | J76: =J96 -> 11697.028 | K76: =K96 -> 13375.357
B77: Other Current Liabilities | D77: ='Grouping OR Separating'!D32 -> 1966 | E77: ='Grouping OR Separating'!E32 -> 919 | F77: ='Grouping OR Separating'!F32 -> 2487 | G77: =F77*(1+G22) -> 3316.8949 | H77: =G77*(1+H22) -> 4142.3343 | I77: =H77*(1+I22) -> 5173.1918 | J77: =I77*(1+J22) -> 6460.5875 | K77: =J77*(1+K22) -> 8068.3633
B78: Total Current Liabilities | D78: =SUM(D73:D77) -> 161335 | E78: =SUM(E73:E77) -> 169452 | F78: =SUM(F73:F77) -> 209177 | G78: =SUM(G73:G77) -> 313915.03 | H78: =SUM(H73:H77) -> 444584.28 | I78: =SUM(I73:I77) -> 574371.5 | J78: =SUM(J73:J77) -> 701385.91 | K78: =SUM(K73:K77) -> 823880.52
B80: Total Liabilities | D80: =D71+D78 -> 426734 | E80: =E71+E78 -> 586630 | F80: =F71+F78 -> 622930 | G80: =G71+G78 -> 728726.56 | H80: =H71+H78 -> 861486.19 | I80: =I71+I78 -> 994258.03 | J80: =J71+J78 -> 1124967.7 | K80: =K71+K78 -> 1251826.9
B82: Share Capital | D82: 381071 | E82: 399555 | F82: 404847 | G82: =G117 -> 410139 | H82: =H117 -> 415431 | I82: =I117 -> 420723 | J82: =J117 -> 426015 | K82: =K117 -> 431307
B83: Non-Distributable Reserves | D83: -2992 | E83: -31154 | F83: -67928 | G83: =F83 -> -67928 | H83: =G83 -> -67928 | I83: =H83 -> -67928 | J83: =I83 -> -67928 | K83: =J83 -> -67928
B84: Retained Earnings (Distributable Reserves) | D84: 252926 | E84: 298012 | F84: 363213 | G84: =G122 -> 435733.4 | H84: =H122 -> 537899.8 | I84: =I122 -> 676882.21 | J84: =J122 -> 863227.63 | K84: =K122 -> 1110194.9
B85: Non-Controlling Interests | D85: 4897 | E85: 26558 | F85: 28107 | G85: =F85 -> 28107 | H85: =G85 -> 28107 | I85: =H85 -> 28107 | J85: =I85 -> 28107 | K85: =J85 -> 28107
B86: Total Equity | D86: =SUM(D82:D85) -> 635902 | E86: =SUM(E82:E85) -> 692971 | F86: =SUM(F82:F85) -> 728239 | G86: =SUM(G82:G85) -> 806051.4 | H86: =SUM(H82:H85) -> 913509.8 | I86: =SUM(I82:I85) -> 1057784.2 | J86: =SUM(J82:J85) -> 1249421.6 | K86: =SUM(K82:K85) -> 1501680.9
B88: Total Equity and Liabilities | D88: =D80+D86 -> 1062636 | E88: =E80+E86 -> 1279601 | F88: =F80+F86 -> 1351169 | G88: =G80+G86 -> 1534778 | H88: =H80+H86 -> 1774996 | I88: =I80+I86 -> 2052042.2 | J88: =J80+J86 -> 2374389.4 | K88: =K80+K86 -> 2753507.9
B89: Balance? | D89: =D66-D88 -> 0 | E89: =E66-E88 -> 0 | F89: =F66-F88 -> 0 | G89: =G66-G88 -> 0 | H89: =H66-H88 -> 0 | I89: =I66-I88 -> 0 | J89: =J66-J88 -> 0 | K89: =K66-K88 -> 0
B91: Memo: Total Debt | D91: =D68+D69+D73+D74+D76 -> 346669 | E91: =E68+E69+E73+E74+E76 -> 430765 | F91: =F68+F69+F73+F74+F76 -> 426883 | G91: =G68+G69+G73+G74+G76 -> 496251.61 | H91: =H68+H69+H73+H74+H76 -> 592778.87 | I91: =I68+I69+I73+I74+I76 -> 680301.57 | J91: =J68+J69+J73+J74+J76 -> 754501.5 | K91: =K68+K69+K73+K74+K76 -> 810787.94
A94: x | B94: Schedules
B95: Lease Liabilities
B96: Lease Liabilities (Short-Term) | D96: {=D76:F76} -> 2293 | E96: 8010 | F96: 8389 | G96: =G100*G97 -> 8324.5621 | H96: =H100*H97 -> 9128.382 | I96: =I100*I97 -> 10276.063 | J96: =J100*J97 -> 11697.028 | K96: =K100*K97 -> 13375.357
B97: % of total lease liabilities | D97: =D96/D100 -> 0.22011466 | E97: =E96/E100 -> 0.32360632 | F97: =F96/F100 -> 0.28948251 | G97: =AVERAGE(D97:F97) -> 0.2777345 | H97: =G97 -> 0.2777345 | I97: =H97 -> 0.2777345 | J97: =I97 -> 0.2777345 | K97: =J97 -> 0.2777345
B98: Lease Liabilities (Long-Term) | D98: {=D69:F69} -> 8124 | E98: 16742 | F98: 20590 | G98: =G100*G99 -> 21648.532 | H98: =H100*H99 -> 23738.914 | I98: =I100*I99 -> 26723.529 | J98: =J100*J99 -> 30418.836 | K98: =K100*K99 -> 34783.431
B99: % of total lease liabilities | D99: =D98/D100 -> 0.77985673 | E99: =E98/E100 -> 0.67638164 | F99: =F98/F100 -> 0.7105072 | G99: =1-G97 -> 0.7222655 | H99: =1-H97 -> 0.7222655 | I99: =1-I97 -> 0.7222655 | J99: =1-J97 -> 0.7222655 | K99: =1-K97 -> 0.7222655
B100: Total Lease Liabilities | D100: =D112 -> 10417.298 | E100: =E112 -> 24752.298 | F100: =F112 -> 28979.298 | G100: =G112 -> 29973.094 | H100: =H112 -> 32867.296 | I100: =I112 -> 36999.593 | J100: =J112 -> 42115.864 | K100: =K112 -> 48158.788
B102: Lease Liabilities - Opening Balance | D102: 6879.298 | E102: =D112 -> 10417.298 | F102: =E112 -> 24752.298 | G102: =F112 -> 28979.298 | H102: =G112 -> 29973.094 | I102: =H112 -> 32867.296 | J102: =I112 -> 36999.593 | K102: =J112 -> 42115.864
B103: Finance Cost | D103: 351.248 | E103: 1198 | F103: 1545 | G103: =F100*G104 -> 1808.8428 | H103: =G100*H104 -> 1870.874 | I103: =H100*I104 -> 2051.5256 | J103: =I100*J104 -> 2309.4571 | K103: =J100*K104 -> 2628.8068
B104: % of Opening Lease Liability | E104: =E103/D100 -> 0.11500103 | F104: =F103/E100 -> 0.062418447 | G104: =F104 -> 0.062418447 | H104: =G104 -> 0.062418447 | I104: =H104 -> 0.062418447 | J104: =I104 -> 0.062418447 | K104: =J104 -> 0.062418447
B105: Repayment of Lease Liabilities | D105: -1335.138 | E105: -8098 | F105: -10425 | G105: =-F100*G106 -> -17366.336 | H105: =-G100*H106 -> -17961.884 | I105: =-H100*I106 -> -19696.285 | J105: =-I100*J106 -> -22172.633 | K105: =-J100*K106 -> -25238.645
B106: % of Opening Lease Liability | E106: =-E105/D100 -> 0.77736089 | F106: =-F105/E100 -> 0.42117302 | G106: =AVERAGE(E106:F106) -> 0.59926695 | H106: =G106 -> 0.59926695 | I106: =H106 -> 0.59926695 | J106: =I106 -> 0.59926695 | K106: =J106 -> 0.59926695
B107: Acquisition of New Assets | D107: 4924.564 | E107: 10640 | F107: 15034 | G107: =G39*G108 -> 16551.288 | H107: =H39*H108 -> 18985.213 | I107: =I39*I108 -> 21777.055 | J107: =J39*J108 -> 24979.447 | K107: =K39*K108 -> 28652.762
B108: Ratio of ROU additions | D108: =D107/D39 -> 0.71494832 | E108: =E107/E39 -> 0.89022758 | F108: =F107/F39 -> 1 | G108: =F108 -> 1 | H108: =G108 -> 1 | I108: =H108 -> 1 | J108: =I108 -> 1 | K108: =J108 -> 1
B109: Others | D109: 0 | E109: 11437 | F109: -279 | G109: 0 | H109: 0 | I109: 0 | J109: 0 | K109: 0
B110: Derecognition of Lease | D110: -368.256 | E110: -901 | F110: -1466 | G110: 0 | H110: =G110*(1+H21) -> 0 | I110: =H110*(1+I21) -> 0 | J110: =I110*(1+J21) -> 0 | K110: =J110*(1+K21) -> 0
B111: Exchange Difference | D111: -34.418 | E111: 59 | F111: -182 | G111: 0 | H111: 0 | I111: 0 | J111: 0 | K111: 0
B112: Lease Liabilities - Closing Balance | D112: =D102+D103+D105+D107+D110+D111+D109 -> 10417.298 | E112: =E102+E103+E105+E107+E110+E111+E109 -> 24752.298 | F112: =F102+F103+F105+F107+F110+F111+F109 -> 28979.298 | G112: =G102+G103+G105+G107+G110+G111+G109 -> 29973.094 | H112: =H102+H103+H105+H107+H110+H111+H109 -> 32867.296 | I112: =I102+I103+I105+I107+I110+I111+I109 -> 36999.593 | J112: =J102+J103+J105+J107+J110+J111+J109 -> 42115.864 | K112: =K102+K103+K105+K107+K110+K111+K109 -> 48158.788
B114: Equity
B115: Share Capital - BOP | G115: =F82 -> 404847 | H115: =G117 -> 410139 | I115: =H117 -> 415431 | J115: =I117 -> 420723 | K115: =J117 -> 426015
B116: Shares Issuance | G116: 5292 | H116: =G116 -> 5292 | I116: =H116 -> 5292 | J116: =I116 -> 5292 | K116: =J116 -> 5292
B117: Share Capital - EOP | G117: =G115+G116 -> 410139 | H117: =H115+H116 -> 415431 | I117: =I115+I116 -> 420723 | J117: =J115+J116 -> 426015 | K117: =K115+K116 -> 431307
B119: Retained Earnings - BOP | G119: =F84 -> 363213 | H119: =G122 -> 435733.4 | I119: =H122 -> 537899.8 | J119: =I122 -> 676882.21 | K119: =J122 -> 863227.63
B120: Net Income | G120: =G17 -> 113748.4 | H120: =H17 -> 143394.4 | I120: =I17 -> 180210.41 | J120: =J17 -> 227573.42 | K120: =K17 -> 288195.28
B121: Dividend Payout | G121: -41228 | H121: =G121 -> -41228 | I121: =H121 -> -41228 | J121: =I121 -> -41228 | K121: =J121 -> -41228
B122: Retained Earnings - EOP | G122: =SUM(G119:G121) -> 435733.4 | H122: =SUM(H119:H121) -> 537899.8 | I122: =SUM(I119:I121) -> 676882.21 | J122: =SUM(J119:J121) -> 863227.63 | K122: =SUM(K119:K121) -> 1110194.9
A125: x | B125: Statement of Cash Flows
B126: Net Income (GAAP) | G126: =G17 -> 113748.4 | H126: =H17 -> 143394.4 | I126: =I17 -> 180210.41 | J126: =J17 -> 227573.42 | K126: =K17 -> 288195.28
...

Sheet DCF
A1: RM'000
D2: FY2025A | E2: FY2026E | F2: FY2027E | G2: FY2028E | H2: FY2029E | I2: FY2030E | J2: Terminal Year (Normalized)
A3: x | B3: Extracted From 3-Statement Model | L3: Farm Fresh in FY2030 is in its high-growth phase
B4: EBIT | D4: ='3-Statement'!F10 -> 131843 | E4: ='3-Statement'!G10 -> 139749.09 | F4: ='3-Statement'!H10 -> 174526.91 | G4: ='3-Statement'!I10 -> 217959.52 | H4: ='3-Statement'!J10 -> 272200.72 | I4: ='3-Statement'!K10 -> 339940.34 | J4: =I4*(1+D49) -> 354217.84 | L4: A DCF's terminal value assumes company grows at constant rate forever
B5: D&A | D5: =-('3-Statement'!F30+'3-Statement'!F35+'3-Statement'!F38) -> 58517 | E5: ='3-Statement'!G127 -> 61336.143 | F5: ='3-Statement'!H127 -> 68151.333 | G5: ='3-Statement'!I127 -> 74675.148 | H5: ='3-Statement'!J127 -> 80707.751 | I5: ='3-Statement'!K127 -> 86074.934 | J5: =I5*(1+D49) -> 89690.081 | L5: So, we have to create a normalized terminal year as a proxy for Farm Fresh in mature, steady state
B6: EBITDA | D6: =D4+D5 -> 190360 | E6: =E4+E5 -> 201085.23 | F6: =F4+F5 -> 242678.25 | G6: =G4+G5 -> 292634.67 | H6: =H4+H5 -> 352908.47 | I6: =I4+I5 -> 426015.28 | J6: =J4+J5 -> 443907.92
L7: D&A = CAPEX because in steady state, company stopped expanding and scaling capacity
B8: Tax Rate | C8: ='3-Statement'!G28 -> 0.065131137 | L8: Company is simply replacing worn-out fixed assets
B10: CAPEX | E10: ='3-Statement'!G48 -> 147724.34 | F10: ='3-Statement'!H48 -> 153836.08 | G10: ='3-Statement'!I48 -> 157931.21 | H10: ='3-Statement'!J48 -> 160121.85 | I10: ='3-Statement'!K48 -> 160754.37 | J10: =J5 -> 89690.081 | L10: Change in NWC also has to get scaled down to grow at steady-state growth
B12: Inventories | E12: ='3-Statement'!G128 -> -58507.091 | F12: ='3-Statement'!H128 -> -58192.98 | G12: ='3-Statement'!I128 -> -72674.831 | H12: ='3-Statement'!J128 -> -90760.622 | I12: ='3-Statement'!K128 -> -113347.23
B13: Receivables | E13: ='3-Statement'!G129 -> -51430.461 | F13: ='3-Statement'!H129 -> -64229.397 | G13: ='3-Statement'!I129 -> -80213.466 | H13: ='3-Statement'!J129 -> -100175.31 | I13: ='3-Statement'!K129 -> -125104.85
B14: Other Current Assets | E14: ='3-Statement'!G130 -> -17312.877 | F14: ='3-Statement'!H130 -> -21621.343 | G14: ='3-Statement'!I130 -> -27002.011 | H14: ='3-Statement'!J130 -> -33721.706 | I14: ='3-Statement'!K130 -> -42113.659
B15: Payables | E15: ='3-Statement'!G131 -> 35598.054 | F15: ='3-Statement'!H131 -> 35406.936 | G15: ='3-Statement'!I131 -> 44218.273 | H15: ='3-Statement'!J131 -> 55222.392 | I15: ='3-Statement'!K131 -> 68964.985
B16: Other Current Liabilities | E16: ='3-Statement'!G132 -> 829.89491 | F16: ='3-Statement'!H132 -> 825.4394 | G16: ='3-Statement'!I132 -> 1030.8575 | H16: ='3-Statement'!J132 -> 1287.3957 | I16: ='3-Statement'!K132 -> 1607.7758
B17: Change in NWC | E17: =SUM(E12:E16) -> -90822.48 | F17: =SUM(F12:F16) -> -107811.35 | G17: =SUM(G12:G16) -> -134641.18 | H17: =SUM(H12:H16) -> -168147.86 | I17: =SUM(I12:I16) -> -209992.97 | J17: =I17*(D49/'3-Statement'!G21) -> -35440.56
R18: =D6/-'3-Statement'!F13 -> 10.771842
A20: x | B20: WACC
B21: Debt
B22: Interest Expense | D22: ='3-Statement'!F13 -> -17672
B23: Total Debt | D23: ='3-Statement'!F91 -> 426883
B24: Cost of Debt | D24: =-D22/D23 -> 0.04139776 | N24: ='3-Statement'!D10-('3-Statement'!D30+'3-Statement'!D35+'3-Statement'!D38) -> 96867 | O24: ='3-Statement'!E10-('3-Statement'!E30+'3-Statement'!E35+'3-Statement'!E38) -> 133594 | P24: =D6 -> 190360 | Q24: =E6 -> 201085.23 | R24: =F6 -> 242678.25 | S24: =G6 -> 292634.67 | T24: =H6 -> 352908.47 | U24: =I6 -> 426015.28
N25: ='3-Statement'!D91 -> 346669 | O25: ='3-Statement'!E91 -> 430765 | P25: ='3-Statement'!F91 -> 426883 | Q25: ='3-Statement'!G91 -> 496251.61 | R25: ='3-Statement'!H91 -> 592778.87 | S25: ='3-Statement'!I91 -> 680301.57 | T25: ='3-Statement'!J91 -> 754501.5 | U25: ='3-Statement'!K91 -> 810787.94
B26: Equity | N26: =N24/-'3-Statement'!D13 -> 8.1134936 | O26: =O24/-'3-Statement'!E13 -> 7.9143365 | P26: =P24/-'3-Statement'!F13 -> 10.771842 | Q26: =Q24/-'3-Statement'!G13 -> 10.50094 | R26: =R24/-'3-Statement'!H13 -> 10.901488 | S26: =S24/-'3-Statement'!I13 -> 11.004997 | T26: =T24/-'3-Statement'!J13 -> 11.56425 | U26: =U24/-'3-Statement'!K13 -> 12.586991
B27: Risk-Free Rate (10y government bond yield) | D27: 0.03747 | F27: https://www.worldgovernmentbonds.com/country/malaysia/
B28: Levered Beta of Farm Fresh (1Y) | D28: 0.74 | F28: https://www.tradingview.com/symbols/MYX-FFB/
B29: Equity Risk Premium | D29: 0.0504 | F29: https://pages.stern.nyu.edu/~adamodar/New_Home_Page/datafile/ctryprem.html
B30: Cost of Equity | D30: =D27+D28*D29 -> 0.074766 | F30: CAPM Model
B32: Share
B33: Market Capitalization (as of 11/8) | D33: 4184000 | F33: https://finance.yahoo.com/quote/5306.KL/
B34: Total Capital Structure | D34: =D33+D23 -> 4610883
B35: Share of Debt | D35: =D23/D34 -> 0.092581616
B36: Share of Equity | D36: =D33/D34 -> 0.90741838
B38: WACC | D38: =(D36*D30)+D35*(D24*(1-C8)) -> 0.071427088
A41: x | B41: FCF Calculation
B42: EBIT | E42: =E4 -> 139749.09 | F42: =F4 -> 174526.91 | G42: =G4 -> 217959.52 | H42: =H4 -> 272200.72 | I42: =I4 -> 339940.34 | J42: =J4 -> 354217.84
A43: (-) | B43: Taxes | E43: =(E42*$C$8)*-1 -> -9102.0169 | F43: =(F42*$C$8)*-1 -> -11367.136 | G43: =(G42*$C$8)*-1 -> -14195.951 | H43: =(H42*$C$8)*-1 -> -17728.743 | I43: =(I42*$C$8)*-1 -> -22140.701 | J43: =-J42*C8 -> -23070.611
A44: (+) | B44: D&A | E44: =E5 -> 61336.143 | F44: =F5 -> 68151.333 | G44: =G5 -> 74675.148 | H44: =H5 -> 80707.751 | I44: =I5 -> 86074.934 | J44: =J5 -> 89690.081
A45: (-) | B45: CAPEX | E45: =(E10)*-1 -> -147724.34 | F45: =(F10)*-1 -> -153836.08 | G45: =(G10)*-1 -> -157931.21 | H45: =(H10)*-1 -> -160121.85 | I45: =(I10)*-1 -> -160754.37 | J45: =-J10 -> -89690.081
A46: (-) | B46: Change in NWC | E46: =E17 -> -90822.48 | F46: =F17 -> -107811.35 | G46: =G17 -> -134641.18 | H46: =H17 -> -168147.86 | I46: =I17 -> -209992.97 | J46: =J17 -> -35440.56
B47: Annual Unlevered FCF | E47: =SUM(E42:E46) -> -46563.608 | F47: =SUM(F42:F46) -> -30336.311 | G47: =SUM(G42:G46) -> -14133.676 | H47: =SUM(H42:H46) -> 6910.0233 | I47: =SUM(I42:I46) -> 33127.228 | J47: =SUM(J42:J46) -> 295706.67
B49: Growth Rate (Malaysia's GDP Growth Rate 10y) | D49: 0.042 | F49: https://www.focus-economics.com/country-indicator/malaysia/gdp/
B50: Terminal Value | D50: =(J47)/(D38-D49) -> 10048791
B52: Enterprise Value | D52: =NPV(D38,E47:I47)+D50/(1+D38)^5 -> 7064390.4
B53: (-) Total Debt | D53: =-D23 -> -426883
B54: (+) Cash | D54: ='3-Statement'!F61 -> 58785
B55: Equity Value | D55: =D52+D53+D54 -> 6696292.4
B56: Implied Equity Premium (Multiple) | D56: =D55/D33 -> 1.6004523
A59: x | B59: Sensitivity Analysis (for IC memo)
B61: Exit Multiple | C61: Exit Equity Value | D61: MOIC | E61: IRR
B62: 23.9 | C62: =($I$6*B62)-'3-Statement'!$K$91+'3-Statement'!$K$61 -> 9520011.5 | D62: =C62/$D$33 -> 2.2753374 | E62: =(D62)^(1/5)-1 -> 0.17871595
B63: 22.27 | C63: =($I$6*B63)-'3-Statement'!$K$91+'3-Statement'!$K$61 -> 8825606.6 | D63: =C63/$D$33 -> 2.1093706 | E63: =(D63)^(1/5)-1 -> 0.16099561
B64: 12.09 | C64: =($I$6*B64)-'3-Statement'!$K$91+'3-Statement'!$K$61 -> 4488771.1 | D64: =C64/$D$33 -> 1.072842 | E64: =(D64)^(1/5)-1 -> 0.014161586
B65: =D50/J6 -> 22.637108 | C65: =($I$6*B65)-'3-Statement'!$K$91+'3-Statement'!$K$61 -> 8982000 | D65: =C65/$D$33 -> 2.1467495 | E65: =(D65)^(1/5)-1 -> 0.16508142
